custom_classifier/__init__.py
custom_classifier/custom_classification.py
temp_dec/__init__.py
temp_dec/decoding_functions.py
temp_dec/select_features.py
temp_dec-1.0.9.dist-info/LICENSE.txt
temp_dec-1.0.9.dist-info/METADATA
temp_dec-1.0.9.dist-info/WHEEL
temp_dec-1.0.9.dist-info/top_level.txt
temp_dec-1.0.9.dist-info/RECORD
