Metadata-Version: 2.1
Name: temp-dec
Version: 1.0.9
Summary: Supervised learning function for temporal decoding.
Home-page: https://github.com/jasperhajonides/temp_dec/archive/v1.0.8.tar.gz
Author: Jasper Hajonides
Author-email: jasperhajonides@gmail.com
License: MIT
Platform: UNKNOWN
Classifier: License :: OSI Approved :: MIT License
Classifier: Programming Language :: Python
Classifier: Programming Language :: Python :: 3
Classifier: Programming Language :: Python :: 3.6
Classifier: Programming Language :: Python :: Implementation :: CPython
Classifier: Programming Language :: Python :: Implementation :: PyPy
Requires-Python: >=3.6.0
Requires-Dist: numpy
Requires-Dist: sklearn
